docker_generate.py
docker_generate-0.1.0.dist-info/entry_points.txt
docker_generate-0.1.0.dist-info/WHEEL
docker_generate-0.1.0.dist-info/METADATA
docker_generate-0.1.0.dist-info/RECORD
